blyg/README.md
blyg/__init__.py
blyg/__main__.py
blyg/args.py
blyg/config.py
blyg/jsonify.py
blyg/output.py
blyg/shy.py
blyg/version.py
blyg/x509.py
blyg/arguments/receive.py
blyg/arguments/upload.py
blyg/receiver/__init__.py
blyg/upload/__init__.py
blyg-0.8.dist-info/METADATA
blyg-0.8.dist-info/WHEEL
blyg-0.8.dist-info/entry_points.txt
blyg-0.8.dist-info/top_level.txt
blyg-0.8.dist-info/RECORD
